juniconnlib_core/__init__.py
juniconnlib_core/_version.py
juniconnlib_core/data_models/__init__.py
juniconnlib_core/data_models/basic_models.py
juniconnlib_core/data_models/fiware_models.py
juniconnlib_core/modules/__init__.py
juniconnlib_core/modules/devtools.py
juniconnlib_core/modules/fiware_iota_communicators.py
juniconnlib_core/modules/fiware_iota_device_provisioner.py
juniconnlib_core/modules/fiware_ocb_communicators.py
juniconnlib_core/modules/fiware_ocb_entity_provisioner.py
juniconnlib_core/modules/fiware_subscriptions.py
juniconnlib_core/modules/influxdb_writer.py
juniconnlib_core/modules/json_schema_parser.py
juniconnlib_core/utils/__init__.py
juniconnlib_core/utils/keycloak_iota.py
juniconnlib_core/utils/keycloak_oauth.py
juniconnlib_core/utils/keycloak_ocb.py
juniconnlib_core/utils/location_fiware_provisioner.py
juniconnlib_core/utils/logging.py
juniconnlib_core/utils/meta.py
juniconnlib_core/utils/mqtt.py
juniconnlib_core/utils/validators.py
juniconnlib_core-1.2.0.dist-info/licenses/LICENSE
juniconnlib_core-1.2.0.dist-info/METADATA
juniconnlib_core-1.2.0.dist-info/WHEEL
juniconnlib_core-1.2.0.dist-info/top_level.txt
juniconnlib_core-1.2.0.dist-info/RECORD
