Metadata-Version: 2.4
Name: juniconnlib-core
Version: 1.2.0
Summary: Core library for FIWARE adpater agents based on EBC AgentLib.
Author-email: "ICE-1, Forschungszentrum Juelich GmbH" <ice-1-fiware-admin@fz-juelich.de>
Maintainer-email: Sascha Johnen <sa.johnen@fz-juelich.de>, Marcel Schroeder <m.schroeder@fz-juelich.de>, Jana Pick <j.pick@fz-juelich.de>
License: MIT License
Project-URL: Homepage, https://jugit.fz-juelich.de/iek-10/public/ict-platform/fiware-applications/juniconnlib-core
Project-URL: Documentation, https://apps.fz-juelich.de/ice-1/ict-platform/juniconnlib-core/
Project-URL: Repository, https://jugit.fz-juelich.de/iek-10/public/ict-platform/fiware-applications/juniconnlib-core
Project-URL: Issues, https://jugit.fz-juelich.de/iek-10/public/ict-platform/fiware-applications/juniconnlib-core/-/issues
Keywords: FIWARE,ICE-1,ICT Platform,AgentLib
Classifier: Programming Language :: Python :: 3
Classifier: Programming Language :: Python :: 3.11
Classifier: Programming Language :: Python :: 3.12
Classifier: Operating System :: OS Independent
Requires-Python: >=3.11
License-File: LICENSE
Requires-Dist: pydantic
Requires-Dist: paho-mqtt~=2.0.0
Requires-Dist: requests~=2.32.0
Requires-Dist: httpx~=0.28
Requires-Dist: filip
Requires-Dist: agentlib~=0.8.2
Requires-Dist: fidere
Requires-Dist: influxdb-client~=1.47.0
Requires-Dist: semantic_version
Provides-Extra: test
Requires-Dist: pytest==8.3.4; extra == "test"
Requires-Dist: pytest-mock~=3.14.0; extra == "test"
Provides-Extra: doc
Requires-Dist: sphinx~=8.0.2; extra == "doc"
Requires-Dist: sphinx-versioned-docs~=1.4.0; extra == "doc"
Requires-Dist: sphinx_rtd_theme~=3.0.2; extra == "doc"
Requires-Dist: sphinx-autodoc-typehints~=2.5.0; extra == "doc"
Requires-Dist: sphinxcontrib-napoleon~=0.7; extra == "doc"
Requires-Dist: autodoc_pydantic~=2.2.0; extra == "doc"
Requires-Dist: myst-parser~=4.0.1; extra == "doc"
Dynamic: license-file
